sfctl/__init__.py
sfctl/apiclient.py
sfctl/auth.py
sfctl/commands.py
sfctl/config.py
sfctl/custom_app.py
sfctl/custom_app_type.py
sfctl/custom_chaos.py
sfctl/custom_chaos_schedule.py
sfctl/custom_cluster.py
sfctl/custom_cluster_upgrade.py
sfctl/custom_compose.py
sfctl/custom_container.py
sfctl/custom_exceptions.py
sfctl/custom_health.py
sfctl/custom_is.py
sfctl/custom_node.py
sfctl/custom_property.py
sfctl/custom_service.py
sfctl/custom_settings.py
sfctl/entry.py
sfctl/params.py
sfctl/send_telemetry_background.py
sfctl/state.py
sfctl/telemetry.py
sfctl/util.py
sfctl/helps/__init__.py
sfctl/helps/app.py
sfctl/helps/app_type.py
sfctl/helps/chaos.py
sfctl/helps/cluster_upgrade.py
sfctl/helps/compose.py
sfctl/helps/container.py
sfctl/helps/health.py
sfctl/helps/infrastructure.py
sfctl/helps/main.py
sfctl/helps/node.py
sfctl/helps/property.py
sfctl/helps/settings.py
sfctl/tests/__init__.py
sfctl/tests/app_test.py
sfctl/tests/chaos_schedule_test.py
sfctl/tests/chaos_test.py
sfctl/tests/cluster_test.py
sfctl/tests/command_processing_test.py
sfctl/tests/custom_help_text_correctness_test.py
sfctl/tests/health_test.py
sfctl/tests/help_text_test.py
sfctl/tests/helpers.py
sfctl/tests/live_scenario_test.py
sfctl/tests/mock_server.py
sfctl/tests/request_generation_body_validation.py
sfctl/tests/request_generation_test.py
sfctl/tests/scenario_test.py
sfctl/tests/service_test.py
sfctl/tests/version_test.py
sfctl-11.2.1.dist-info/LICENSE.txt
sfctl-11.2.1.dist-info/METADATA
sfctl-11.2.1.dist-info/WHEEL
sfctl-11.2.1.dist-info/entry_points.txt
sfctl-11.2.1.dist-info/top_level.txt
sfctl-11.2.1.dist-info/RECORD
