Metadata-Version: 2.1
Name: sfctl
Version: 11.2.1
Summary: Azure Service Fabric command line
Home-page: https://github.com/Azure/service-fabric-cli
Author: Microsoft Corporation
Author-email: sfpythoncli@microsoft.com
License: MIT
Keywords: servicefabric azure
Classifier: Development Status :: 5 - Production/Stable
Classifier: Intended Audience :: Developers
Classifier: Topic :: Software Development :: Build Tools
Classifier: Environment :: Console
Classifier: License :: OSI Approved :: MIT License
Classifier: Natural Language :: English
Classifier: Programming Language :: Python :: 3.8
Classifier: Programming Language :: Python :: 3.9
Classifier: Programming Language :: Python :: 3.10
Requires-Python: >3.8, <4
License-File: LICENSE.txt
Requires-Dist: knack ==0.6.3
Requires-Dist: requests ==2.32.3
Requires-Dist: msrest >=0.5.0
Requires-Dist: msrestazure
Requires-Dist: azure-servicefabric ==8.2.0.0
Requires-Dist: adal
Requires-Dist: future
Requires-Dist: applicationinsights
Requires-Dist: psutil
Requires-Dist: portalocker
Requires-Dist: six
Requires-Dist: joblib ==1.4.2
Requires-Dist: tqdm
Provides-Extra: test
Requires-Dist: coverage ; extra == 'test'
Requires-Dist: nose2 ; extra == 'test'
Requires-Dist: pylint ==2.7.2 ; extra == 'test'
Requires-Dist: vcrpy ; extra == 'test'
Requires-Dist: mock ; extra == 'test'
Requires-Dist: contextlib2 ; extra == 'test'
